{
  "date": "2025-03-12",
  "data": [
    {
      "lastYearRptDt": "3/14/2024",
      "lastYearEPS": "$3.53",
      "time": "time-after-hours",
      "symbol": "ADBE",
      "name": "Adobe Inc.",
      "marketCap": "$188,772,198,000",
      "fiscalQuarterEnding": "Feb/2025",
      "epsForecast": "$4.07",
      "noOfEsts": "12"
    },
    {
      "lastYearRptDt": "1/24/2024",
      "lastYearEPS": "$1.82",
      "time": "time-after-hours",
      "symbol": "CCI",
      "name": "Crown Castle Inc.",
      "marketCap": "$42,429,823,047",
      "fiscalQuarterEnding": "Dec/2024",
      "epsForecast": "$1.74",
      "noOfEsts": "6"
    },
    {
      "lastYearRptDt": "3/13/2024",
      "lastYearEPS": "$2.72",
      "time": "time-not-supplied",
      "symbol": "WSM",
      "name": "Williams-Sonoma, Inc.",
      "marketCap": "$21,532,642,030",
      "fiscalQuarterEnding": "Jan/2025",
      "epsForecast": "$2.91",
      "noOfEsts": "9"
    },
    {
      "lastYearRptDt": "3/13/2024",
      "lastYearEPS": "$0.06",
      "time": "time-after-hours",
      "symbol": "PATH",
      "name": "UiPath, Inc.",
      "marketCap": "$6,452,291,426",
      "fiscalQuarterEnding": "Jan/2025",
      "epsForecast": "$0.04",
      "noOfEsts": "6"
    },
    {
      "lastYearRptDt": "3/13/2024",
      "lastYearEPS": "($0.21)",
      "time": "time-after-hours",
      "symbol": "S",
      "name": "SentinelOne, Inc.",
      "marketCap": "$6,025,153,013",
      "fiscalQuarterEnding": "Jan/2025",
      "epsForecast": "($0.18)",
      "noOfEsts": "11"
    },
    {
      "lastYearRptDt": "N/A",
      "lastYearEPS": "$8.89",
      "time": "time-not-supplied",
      "symbol": "BMA",
      "name": "Macro Bank Inc.",
      "marketCap": "$5,218,892,252",
      "fiscalQuarterEnding": "Dec/2024",
      "epsForecast": "$2.41",
      "noOfEsts": "2"
    },
    {
      "lastYearRptDt": "3/27/2024",
      "lastYearEPS": "($0.51)",
      "time": "time-pre-market",
      "symbol": "VNET",
      "name": "VNET Group, Inc.",
      "marketCap": "$3,179,567,240",
      "fiscalQuarterEnding": "Dec/2024",
      "epsForecast": "$0.03",
      "noOfEsts": "1"
    },
    {
      "lastYearRptDt": "3/07/2024",
      "lastYearEPS": "$0.86",
      "time": "time-pre-market",
      "symbol": "ABM",
      "name": "ABM Industries Incorporated",
      "marketCap": "$3,099,593,977",
      "fiscalQuarterEnding": "Jan/2025",
      "epsForecast": "$0.78",
      "noOfEsts": "5"
    },
    {
      "lastYearRptDt": "3/13/2024",
      "lastYearEPS": "($1.23)",
      "time": "time-pre-market",
      "symbol": "ZIM",
      "name": "ZIM Integrated Shipping Services Ltd.",
      "marketCap": "$2,443,021,394",
      "fiscalQuarterEnding": "Dec/2024",
      "epsForecast": "$3.47",
      "noOfEsts": "3"
    },
    {
      "lastYearRptDt": "3/07/2024",
      "lastYearEPS": "$0.61",
      "time": "time-after-hours",
      "symbol": "AEO",
      "name": "American Eagle Outfitters, Inc.",
      "marketCap": "$2,207,249,487",
      "fiscalQuarterEnding": "Jan/2025",
      "epsForecast": "$0.50",
      "noOfEsts": "7"
    },
    {
      "lastYearRptDt": "3/27/2024",
      "lastYearEPS": "$0.07",
      "time": "time-pre-market",
      "symbol": "CXM",
      "name": "Sprinklr, Inc.",
      "marketCap": "$2,055,413,097",
      "fiscalQuarterEnding": "Jan/2025",
      "epsForecast": "$0.02",
      "noOfEsts": "6"
    },
    {
      "lastYearRptDt": "3/07/2024",
      "lastYearEPS": "$0.13",
      "time": "time-after-hours",
      "symbol": "SID",
      "name": "National Steel Company",
      "marketCap": "$1,949,358,102",
      "fiscalQuarterEnding": "Dec/2024",
      "epsForecast": "($0.09)",
      "noOfEsts": "1"
    },
    {
      "lastYearRptDt": "3/13/2024",
      "lastYearEPS": "$0.27",
      "time": "time-pre-market",
      "symbol": "ARCO",
      "name": "Arcos Dorados Holdings Inc.",
      "marketCap": "$1,643,108,758",
      "fiscalQuarterEnding": "Dec/2024",
      "epsForecast": "$0.22",
      "noOfEsts": "1"
    },
    {
      "lastYearRptDt": "3/15/2024",
      "lastYearEPS": "($0.16)",
      "time": "time-pre-market",
      "symbol": "EH",
      "name": "EHang Holdings Limited",
      "marketCap": "$1,425,703,885",
      "fiscalQuarterEnding": "Dec/2024",
      "epsForecast": "",
      "noOfEsts": "N/A"
    },
    {
      "lastYearRptDt": "3/14/2024",
      "lastYearEPS": "$0.33",
      "time": "time-pre-market",
      "symbol": "MOMO",
      "name": "Hello Group Inc. ",
      "marketCap": "$1,391,566,062",
      "fiscalQuarterEnding": "Dec/2024",
      "epsForecast": "$0.17",
      "noOfEsts": "1"
    },
    {
      "lastYearRptDt": "3/14/2024",
      "lastYearEPS": "($0.56)",
      "time": "time-after-hours",
      "symbol": "PHR",
      "name": "Phreesia, Inc.",
      "marketCap": "$1,350,222,425",
      "fiscalQuarterEnding": "Jan/2025",
      "epsForecast": "($0.19)",
      "noOfEsts": "5"
    },
    {
      "lastYearRptDt": "N/A",
      "lastYearEPS": "$2.16",
      "time": "time-not-supplied",
      "symbol": "UVV",
      "name": "Universal Corporation",
      "marketCap": "$1,339,581,525",
      "fiscalQuarterEnding": "Dec/2024",
      "epsForecast": "",
      "noOfEsts": "2"
    },
    {
      "lastYearRptDt": "3/13/2024",
      "lastYearEPS": "($0.15)",
      "time": "time-after-hours",
      "symbol": "NN",
      "name": "NextNav Inc.",
      "marketCap": "$1,309,266,287",
      "fiscalQuarterEnding": "Dec/2024",
      "epsForecast": "($0.14)",
      "noOfEsts": "2"
    },
    {
      "lastYearRptDt": "3/13/2024",
      "lastYearEPS": "($0.42)",
      "time": "time-not-supplied",
      "symbol": "LQDA",
      "name": "Liquidia Corporation",
      "marketCap": "$1,176,449,032",
      "fiscalQuarterEnding": "Dec/2024",
      "epsForecast": "($0.39)",
      "noOfEsts": "6"
    },
    {
      "lastYearRptDt": "3/13/2024",
      "lastYearEPS": "$0.32",
      "time": "time-pre-market",
      "symbol": "NVGS",
      "name": "Navigator Holdings Ltd.",
      "marketCap": "$1,009,546,401",
      "fiscalQuarterEnding": "Dec/2024",
      "epsForecast": "$0.31",
      "noOfEsts": "2"
    },
    {
      "lastYearRptDt": "3/14/2024",
      "lastYearEPS": "$0.07",
      "time": "time-after-hours",
      "symbol": "CINT",
      "name": "CI&T Inc",
      "marketCap": "$873,678,091",
      "fiscalQuarterEnding": "Dec/2024",
      "epsForecast": "",
      "noOfEsts": "N/A"
    },
    {
      "lastYearRptDt": "N/A",
      "lastYearEPS": "N/A",
      "time": "time-pre-market",
      "symbol": "SEAT",
      "name": "Vivid Seats Inc.",
      "marketCap": "$783,199,966",
      "fiscalQuarterEnding": "Dec/2024",
      "epsForecast": "$0.03",
      "noOfEsts": "2"
    },
    {
      "lastYearRptDt": "3/06/2024",
      "lastYearEPS": "$0.09",
      "time": "time-after-hours",
      "symbol": "ARMN",
      "name": "Aris Mining Corporation",
      "marketCap": "$677,837,947",
      "fiscalQuarterEnding": "Dec/2024",
      "epsForecast": "$0.18",
      "noOfEsts": "2"
    },
    {
      "lastYearRptDt": "2/06/2024",
      "lastYearEPS": "($0.57)",
      "time": "time-after-hours",
      "symbol": "ASTL",
      "name": "Algoma Steel Group Inc.",
      "marketCap": "$604,955,048",
      "fiscalQuarterEnding": "Dec/2024",
      "epsForecast": "$0.06",
      "noOfEsts": "1"
    },
    {
      "lastYearRptDt": "3/15/2024",
      "lastYearEPS": "$0.28",
      "time": "time-after-hours",
      "symbol": "LEGH",
      "name": "Legacy Housing Corporation",
      "marketCap": "$600,092,445",
      "fiscalQuarterEnding": "Dec/2024",
      "epsForecast": "",
      "noOfEsts": "N/A"
    },
    {
      "lastYearRptDt": "3/13/2024",
      "lastYearEPS": "($0.01)",
      "time": "time-not-supplied",
      "symbol": "VZLA",
      "name": "Vizsla Silver Corp.",
      "marketCap": "$583,954,821",
      "fiscalQuarterEnding": "Jan/2025",
      "epsForecast": "($0.01)",
      "noOfEsts": "2"
    },
    {
      "lastYearRptDt": "3/13/2024",
      "lastYearEPS": "$0.29",
      "time": "time-not-supplied",
      "symbol": "TH",
      "name": "Target Hospitality Corp.",
      "marketCap": "$534,282,264",
      "fiscalQuarterEnding": "Dec/2024",
      "epsForecast": "$0.07",
      "noOfEsts": "3"
    },
    {
      "lastYearRptDt": "3/26/2024",
      "lastYearEPS": "$0.02",
      "time": "time-pre-market",
      "symbol": "WDH",
      "name": "Waterdrop Inc.",
      "marketCap": "$451,597,885",
      "fiscalQuarterEnding": "Dec/2024",
      "epsForecast": "",
      "noOfEsts": "N/A"
    },
    {
      "lastYearRptDt": "N/A",
      "lastYearEPS": "N/A",
      "time": "time-not-supplied",
      "symbol": "AIRJ",
      "name": "AirJoule Technologies Corporation",
      "marketCap": "$407,655,105",
      "fiscalQuarterEnding": "Dec/2024",
      "epsForecast": "($0.07)",
      "noOfEsts": "2"
    },
    {
      "lastYearRptDt": "3/11/2024",
      "lastYearEPS": "($0.01)",
      "time": "time-after-hours",
      "symbol": "CVGW",
      "name": "Calavo Growers, Inc.",
      "marketCap": "$399,378,289",
      "fiscalQuarterEnding": "Jan/2025",
      "epsForecast": "",
      "noOfEsts": "N/A"
    },
    {
      "lastYearRptDt": "3/14/2024",
      "lastYearEPS": "$0.04",
      "time": "time-after-hours",
      "symbol": "MNTK",
      "name": "Montauk Renewables, Inc.",
      "marketCap": "$397,128,313",
      "fiscalQuarterEnding": "Dec/2024",
      "epsForecast": "$0.05",
      "noOfEsts": "1"
    },
    {
      "lastYearRptDt": "3/07/2024",
      "lastYearEPS": "($0.23)",
      "time": "time-after-hours",
      "symbol": "LMNR",
      "name": "Limoneira Co",
      "marketCap": "$384,265,705",
      "fiscalQuarterEnding": "Jan/2025",
      "epsForecast": "($0.24)",
      "noOfEsts": "1"
    },
    {
      "lastYearRptDt": "N/A",
      "lastYearEPS": "N/A",
      "time": "time-not-supplied",
      "symbol": "SBC",
      "name": "SBC Medical Group Holdings Incorporated",
      "marketCap": "$339,968,693",
      "fiscalQuarterEnding": "Dec/2024",
      "epsForecast": "$0.17",
      "noOfEsts": "2"
    },
    {
      "lastYearRptDt": "3/13/2024",
      "lastYearEPS": "$0.34",
      "time": "time-not-supplied",
      "symbol": "ARTNA",
      "name": "Artesian Resources Corporation",
      "marketCap": "$336,742,802",
      "fiscalQuarterEnding": "Dec/2024",
      "epsForecast": "$0.32",
      "noOfEsts": "1"
    },
    {
      "lastYearRptDt": "3/12/2024",
      "lastYearEPS": "$0.50",
      "time": "time-pre-market",
      "symbol": "REFI",
      "name": "Chicago Atlantic Real Estate Finance, Inc.",
      "marketCap": "$311,795,574",
      "fiscalQuarterEnding": "Dec/2024",
      "epsForecast": "$0.44",
      "noOfEsts": "2"
    },
    {
      "lastYearRptDt": "3/06/2024",
      "lastYearEPS": "($0.02)",
      "time": "time-not-supplied",
      "symbol": "URG",
      "name": "Ur Energy Inc",
      "marketCap": "$302,822,833",
      "fiscalQuarterEnding": "Dec/2024",
      "epsForecast": "($0.05)",
      "noOfEsts": "2"
    },
    {
      "lastYearRptDt": "N/A",
      "lastYearEPS": "N/A",
      "time": "time-not-supplied",
      "symbol": "LPA",
      "name": "Logistic Properties of the Americas",
      "marketCap": "$296,803,232",
      "fiscalQuarterEnding": "Dec/2024",
      "epsForecast": "",
      "noOfEsts": "2"
    },
    {
      "lastYearRptDt": "N/A",
      "lastYearEPS": "N/A",
      "time": "time-not-supplied",
      "symbol": "SEPN",
      "name": "Septerna, Inc.",
      "marketCap": "$296,610,317",
      "fiscalQuarterEnding": "Dec/2024",
      "epsForecast": "($0.56)",
      "noOfEsts": "2"
    },
    {
      "lastYearRptDt": "3/06/2024",
      "lastYearEPS": "$0.13",
      "time": "time-after-hours",
      "symbol": "BRY",
      "name": "Berry Corporation (bry)",
      "marketCap": "$271,594,649",
      "fiscalQuarterEnding": "Dec/2024",
      "epsForecast": "$0.12",
      "noOfEsts": "2"
    },
    {
      "lastYearRptDt": "N/A",
      "lastYearEPS": "$0.22",
      "time": "time-after-hours",
      "symbol": "VSTA",
      "name": "Vasta Platform Limited",
      "marketCap": "$268,117,398",
      "fiscalQuarterEnding": "Dec/2024",
      "epsForecast": "$0.25",
      "noOfEsts": "2"
    },
    {
      "lastYearRptDt": "3/06/2024",
      "lastYearEPS": "($0.52)",
      "time": "time-not-supplied",
      "symbol": "SPIR",
      "name": "Spire Global, Inc.",
      "marketCap": "$266,974,530",
      "fiscalQuarterEnding": "Dec/2024",
      "epsForecast": "($0.97)",
      "noOfEsts": "1"
    },
    {
      "lastYearRptDt": "N/A",
      "lastYearEPS": "N/A",
      "time": "time-not-supplied",
      "symbol": "ALMS",
      "name": "Alumis Inc.",
      "marketCap": "$260,611,096",
      "fiscalQuarterEnding": "Dec/2024",
      "epsForecast": "($1.39)",
      "noOfEsts": "2"
    },
    {
      "lastYearRptDt": "N/A",
      "lastYearEPS": "$0.04",
      "time": "time-not-supplied",
      "symbol": "TATT",
      "name": "TAT Technologies Ltd.",
      "marketCap": "$252,161,196",
      "fiscalQuarterEnding": "Dec/2024",
      "epsForecast": "",
      "noOfEsts": "2"
    },
    {
      "lastYearRptDt": "3/13/2024",
      "lastYearEPS": "$0.05",
      "time": "time-after-hours",
      "symbol": "ANIK",
      "name": "Anika Therapeutics Inc.",
      "marketCap": "$245,899,557",
      "fiscalQuarterEnding": "Dec/2024",
      "epsForecast": "($0.11)",
      "noOfEsts": "1"
    },
    {
      "lastYearRptDt": "2/28/2024",
      "lastYearEPS": "($0.10)",
      "time": "time-not-supplied",
      "symbol": "MVIS",
      "name": "Microvision, Inc.",
      "marketCap": "$238,729,816",
      "fiscalQuarterEnding": "Dec/2024",
      "epsForecast": "",
      "noOfEsts": "N/A"
    },
    {
      "lastYearRptDt": "3/12/2024",
      "lastYearEPS": "$0.14",
      "time": "time-after-hours",
      "symbol": "BTMD",
      "name": "Biote Corp.",
      "marketCap": "$224,412,380",
      "fiscalQuarterEnding": "Dec/2024",
      "epsForecast": "$0.09",
      "noOfEsts": "3"
    },
    {
      "lastYearRptDt": "3/12/2024",
      "lastYearEPS": "$0.02",
      "time": "time-after-hours",
      "symbol": "PHLT",
      "name": "Performant Healthcare, Inc.",
      "marketCap": "$197,294,237",
      "fiscalQuarterEnding": "Dec/2024",
      "epsForecast": "",
      "noOfEsts": "N/A"
    },
    {
      "lastYearRptDt": "2/29/2024",
      "lastYearEPS": "($0.01)",
      "time": "time-pre-market",
      "symbol": "AMRN",
      "name": "Amarin Corporation plc",
      "marketCap": "$193,493,457",
      "fiscalQuarterEnding": "Dec/2024",
      "epsForecast": "($0.06)",
      "noOfEsts": "3"
    },
    {
      "lastYearRptDt": "2/26/2024",
      "lastYearEPS": "($2.18)",
      "time": "time-pre-market",
      "symbol": "IRBT",
      "name": "iRobot Corporation",
      "marketCap": "$192,826,078",
      "fiscalQuarterEnding": "Dec/2024",
      "epsForecast": "($1.67)",
      "noOfEsts": "1"
    },
    {
      "lastYearRptDt": "N/A",
      "lastYearEPS": "($2.82)",
      "time": "time-after-hours",
      "symbol": "LOGC",
      "name": "ContextLogic Inc.",
      "marketCap": "$184,521,086",
      "fiscalQuarterEnding": "Dec/2024",
      "epsForecast": "",
      "noOfEsts": "2"
    },
    {
      "lastYearRptDt": "3/06/2024",
      "lastYearEPS": "$0.27",
      "time": "time-after-hours",
      "symbol": "EARN",
      "name": "Ellington Credit Company",
      "marketCap": "$176,258,111",
      "fiscalQuarterEnding": "Dec/2024",
      "epsForecast": "$0.26",
      "noOfEsts": "1"
    },
    {
      "lastYearRptDt": "3/12/2024",
      "lastYearEPS": "($0.07)",
      "time": "time-after-hours",
      "symbol": "SKIN",
      "name": "The Beauty Health Company",
      "marketCap": "$168,806,135",
      "fiscalQuarterEnding": "Dec/2024",
      "epsForecast": "($0.10)",
      "noOfEsts": "5"
    },
    {
      "lastYearRptDt": "3/13/2024",
      "lastYearEPS": "($1.03)",
      "time": "time-not-supplied",
      "symbol": "ADCT",
      "name": "ADC Therapeutics SA",
      "marketCap": "$166,306,141",
      "fiscalQuarterEnding": "Dec/2024",
      "epsForecast": "($0.39)",
      "noOfEsts": "3"
    },
    {
      "lastYearRptDt": "1/31/2024",
      "lastYearEPS": "$0.17",
      "time": "time-not-supplied",
      "symbol": "BFIN",
      "name": "BankFinancial Corporation",
      "marketCap": "$154,512,407",
      "fiscalQuarterEnding": "Dec/2024",
      "epsForecast": "$0.20",
      "noOfEsts": "2"
    },
    {
      "lastYearRptDt": "3/13/2024",
      "lastYearEPS": "($0.35)",
      "time": "time-not-supplied",
      "symbol": "SCPH",
      "name": "scPharmaceuticals Inc.",
      "marketCap": "$154,123,613",
      "fiscalQuarterEnding": "Dec/2024",
      "epsForecast": "($0.40)",
      "noOfEsts": "4"
    },
    {
      "lastYearRptDt": "3/13/2024",
      "lastYearEPS": "($0.08)",
      "time": "time-not-supplied",
      "symbol": "PRQR",
      "name": "ProQR Therapeutics N.V.",
      "marketCap": "$150,505,995",
      "fiscalQuarterEnding": "Dec/2024",
      "epsForecast": "($0.07)",
      "noOfEsts": "3"
    },
    {
      "lastYearRptDt": "2/28/2024",
      "lastYearEPS": "($0.26)",
      "time": "time-pre-market",
      "symbol": "MX",
      "name": "Magnachip Semiconductor Corporation",
      "marketCap": "$150,299,243",
      "fiscalQuarterEnding": "Dec/2024",
      "epsForecast": "($0.27)",
      "noOfEsts": "2"
    },
    {
      "lastYearRptDt": "3/06/2024",
      "lastYearEPS": "$0.06",
      "time": "time-after-hours",
      "symbol": "AEYE",
      "name": "AudioEye, Inc.",
      "marketCap": "$147,111,810",
      "fiscalQuarterEnding": "Dec/2024",
      "epsForecast": "$0.09",
      "noOfEsts": "2"
    },
    {
      "lastYearRptDt": "3/13/2024",
      "lastYearEPS": "($0.02)",
      "time": "time-after-hours",
      "symbol": "KRMD",
      "name": "KORU Medical Systems, Inc.",
      "marketCap": "$142,554,015",
      "fiscalQuarterEnding": "Dec/2024",
      "epsForecast": "($0.03)",
      "noOfEsts": "2"
    },
    {
      "lastYearRptDt": "N/A",
      "lastYearEPS": "$0.07",
      "time": "time-after-hours",
      "symbol": "PHX",
      "name": "PHX Minerals Inc.",
      "marketCap": "$141,302,578",
      "fiscalQuarterEnding": "Dec/2024",
      "epsForecast": "",
      "noOfEsts": "2"
    },
    {
      "lastYearRptDt": "N/A",
      "lastYearEPS": "$0.85",
      "time": "time-after-hours",
      "symbol": "KEQU",
      "name": "Kewaunee Scientific Corporation",
      "marketCap": "$135,491,901",
      "fiscalQuarterEnding": "Jan/2025",
      "epsForecast": "",
      "noOfEsts": "2"
    },
    {
      "lastYearRptDt": "3/13/2024",
      "lastYearEPS": "$0.71",
      "time": "time-after-hours",
      "symbol": "RCMT",
      "name": "RCM Technologies, Inc.",
      "marketCap": "$132,568,139",
      "fiscalQuarterEnding": "Dec/2024",
      "epsForecast": "",
      "noOfEsts": "N/A"
    },
    {
      "lastYearRptDt": "3/14/2024",
      "lastYearEPS": "$0.02",
      "time": "time-after-hours",
      "symbol": "BRLT",
      "name": "Brilliant Earth Group, Inc.",
      "marketCap": "$130,088,109",
      "fiscalQuarterEnding": "Dec/2024",
      "epsForecast": "($0.03)",
      "noOfEsts": "5"
    },
    {
      "lastYearRptDt": "2/28/2024",
      "lastYearEPS": "($0.39)",
      "time": "time-not-supplied",
      "symbol": "NEON",
      "name": "Neonode Inc.",
      "marketCap": "$129,731,987",
      "fiscalQuarterEnding": "Dec/2024",
      "epsForecast": "",
      "noOfEsts": "N/A"
    },
    {
      "lastYearRptDt": "3/18/2024",
      "lastYearEPS": "($0.07)",
      "time": "time-after-hours",
      "symbol": "RAIL",
      "name": "Freightcar America, Inc.",
      "marketCap": "$122,810,818",
      "fiscalQuarterEnding": "Dec/2024",
      "epsForecast": "$0.05",
      "noOfEsts": "2"
    },
    {
      "lastYearRptDt": "2/28/2024",
      "lastYearEPS": "($3.48)",
      "time": "time-not-supplied",
      "symbol": "VCSA",
      "name": "Vacasa, Inc.",
      "marketCap": "$115,679,743",
      "fiscalQuarterEnding": "Dec/2024",
      "epsForecast": "($3.07)",
      "noOfEsts": "2"
    },
    {
      "lastYearRptDt": "3/06/2024",
      "lastYearEPS": "($0.24)",
      "time": "time-not-supplied",
      "symbol": "ADAP",
      "name": "Adaptimmune Therapeutics plc",
      "marketCap": "$114,379,794",
      "fiscalQuarterEnding": "Dec/2024",
      "epsForecast": "($0.14)",
      "noOfEsts": "4"
    },
    {
      "lastYearRptDt": "3/14/2024",
      "lastYearEPS": "($0.17)",
      "time": "time-after-hours",
      "symbol": "TLYS",
      "name": "Tilly's, Inc.",
      "marketCap": "$107,943,827",
      "fiscalQuarterEnding": "Jan/2025",
      "epsForecast": "($0.28)",
      "noOfEsts": "1"
    },
    {
      "lastYearRptDt": "3/06/2024",
      "lastYearEPS": "($0.08)",
      "time": "time-not-supplied",
      "symbol": "ORMP",
      "name": "Oramed Pharmaceuticals Inc.",
      "marketCap": "$105,617,621",
      "fiscalQuarterEnding": "Dec/2024",
      "epsForecast": "($0.03)",
      "noOfEsts": "2"
    },
    {
      "lastYearRptDt": "3/14/2024",
      "lastYearEPS": "($0.14)",
      "time": "time-after-hours",
      "symbol": "CDLX",
      "name": "Cardlytics, Inc.",
      "marketCap": "$102,661,335",
      "fiscalQuarterEnding": "Dec/2024",
      "epsForecast": "($0.52)",
      "noOfEsts": "1"
    },
    {
      "lastYearRptDt": "2/14/2024",
      "lastYearEPS": "($8.39)",
      "time": "time-not-supplied",
      "symbol": "HURA",
      "name": "TuHURA Biosciences, Inc.",
      "marketCap": "$89,643,191",
      "fiscalQuarterEnding": "Dec/2024",
      "epsForecast": "($0.15)",
      "noOfEsts": "2"
    },
    {
      "lastYearRptDt": "3/12/2024",
      "lastYearEPS": "$0.03",
      "time": "time-after-hours",
      "symbol": "QRHC",
      "name": "Quest Resource Holding Corporation",
      "marketCap": "$88,732,879",
      "fiscalQuarterEnding": "Dec/2024",
      "epsForecast": "$0.03",
      "noOfEsts": "2"
    },
    {
      "lastYearRptDt": "3/13/2024",
      "lastYearEPS": "($0.61)",
      "time": "time-after-hours",
      "symbol": "ECOR",
      "name": "electroCore, Inc.",
      "marketCap": "$86,389,509",
      "fiscalQuarterEnding": "Dec/2024",
      "epsForecast": "($0.34)",
      "noOfEsts": "2"
    },
    {
      "lastYearRptDt": "N/A",
      "lastYearEPS": "($0.21)",
      "time": "time-not-supplied",
      "symbol": "GAN",
      "name": "GAN Limited",
      "marketCap": "$80,659,240",
      "fiscalQuarterEnding": "Dec/2024",
      "epsForecast": "",
      "noOfEsts": "2"
    },
    {
      "lastYearRptDt": "2/22/2024",
      "lastYearEPS": "N/A",
      "time": "time-pre-market",
      "symbol": "UPLD",
      "name": "Upland Software, Inc.",
      "marketCap": "$78,481,168",
      "fiscalQuarterEnding": "Dec/2024",
      "epsForecast": "$0.14",
      "noOfEsts": "2"
    },
    {
      "lastYearRptDt": "3/15/2024",
      "lastYearEPS": "($0.09)",
      "time": "time-after-hours",
      "symbol": "MGRM",
      "name": "Monogram Technologies Inc.",
      "marketCap": "$77,888,832",
      "fiscalQuarterEnding": "Dec/2024",
      "epsForecast": "($0.11)",
      "noOfEsts": "2"
    },
    {
      "lastYearRptDt": "4/16/2024",
      "lastYearEPS": "$0.11",
      "time": "time-pre-market",
      "symbol": "OPRX",
      "name": "OptimizeRx Corporation",
      "marketCap": "$76,262,551",
      "fiscalQuarterEnding": "Dec/2024",
      "epsForecast": "$0.10",
      "noOfEsts": "4"
    },
    {
      "lastYearRptDt": "3/06/2024",
      "lastYearEPS": "($0.54)",
      "time": "time-not-supplied",
      "symbol": "KLXE",
      "name": "KLX Energy Services Holdings, Inc. ",
      "marketCap": "$76,040,115",
      "fiscalQuarterEnding": "Dec/2024",
      "epsForecast": "($0.72)",
      "noOfEsts": "2"
    },
    {
      "lastYearRptDt": "3/13/2024",
      "lastYearEPS": "$0.11",
      "time": "time-pre-market",
      "symbol": "VRA",
      "name": "Vera Bradley, Inc.",
      "marketCap": "$75,277,342",
      "fiscalQuarterEnding": "Jan/2025",
      "epsForecast": "$0.10",
      "noOfEsts": "1"
    },
    {
      "lastYearRptDt": "3/05/2024",
      "lastYearEPS": "($0.16)",
      "time": "time-pre-market",
      "symbol": "NSPR",
      "name": "InspireMD Inc.",
      "marketCap": "$72,773,699",
      "fiscalQuarterEnding": "Dec/2024",
      "epsForecast": "($0.20)",
      "noOfEsts": "1"
    },
    {
      "lastYearRptDt": "N/A",
      "lastYearEPS": "($0.30)",
      "time": "time-after-hours",
      "symbol": "FOSL",
      "name": "Fossil Group, Inc.",
      "marketCap": "$68,088,287",
      "fiscalQuarterEnding": "Dec/2024",
      "epsForecast": "",
      "noOfEsts": "2"
    },
    {
      "lastYearRptDt": "N/A",
      "lastYearEPS": "N/A",
      "time": "time-not-supplied",
      "symbol": "AFJK",
      "name": "Aimei Health Technology Co., Ltd",
      "marketCap": "$65,700,000",
      "fiscalQuarterEnding": "Dec/2024",
      "epsForecast": "",
      "noOfEsts": "2"
    },
    {
      "lastYearRptDt": "3/06/2024",
      "lastYearEPS": "($0.33)",
      "time": "time-not-supplied",
      "symbol": "APLT",
      "name": "Applied Therapeutics, Inc.",
      "marketCap": "$62,844,132",
      "fiscalQuarterEnding": "Dec/2024",
      "epsForecast": "($0.15)",
      "noOfEsts": "1"
    },
    {
      "lastYearRptDt": "3/14/2024",
      "lastYearEPS": "$0.13",
      "time": "time-pre-market",
      "symbol": "DTC",
      "name": "Solo Brands, Inc.",
      "marketCap": "$60,044,905",
      "fiscalQuarterEnding": "Dec/2024",
      "epsForecast": "$0.10",
      "noOfEsts": "2"
    },
    {
      "lastYearRptDt": "3/18/2024",
      "lastYearEPS": "($0.21)",
      "time": "time-after-hours",
      "symbol": "CMTL",
      "name": "Comtech Telecommunications Corp.",
      "marketCap": "$58,925,184",
      "fiscalQuarterEnding": "Jan/2025",
      "epsForecast": "($0.60)",
      "noOfEsts": "2"
    },
    {
      "lastYearRptDt": "4/01/2024",
      "lastYearEPS": "($0.26)",
      "time": "time-pre-market",
      "symbol": "ONDS",
      "name": "Ondas Holdings Inc.",
      "marketCap": "$55,921,166",
      "fiscalQuarterEnding": "Dec/2024",
      "epsForecast": "($0.09)",
      "noOfEsts": "2"
    },
    {
      "lastYearRptDt": "3/13/2024",
      "lastYearEPS": "($0.03)",
      "time": "time-not-supplied",
      "symbol": "GORO",
      "name": "Gold Resource Corporation",
      "marketCap": "$52,895,814",
      "fiscalQuarterEnding": "Dec/2024",
      "epsForecast": "",
      "noOfEsts": "N/A"
    },
    {
      "lastYearRptDt": "N/A",
      "lastYearEPS": "N/A",
      "time": "time-not-supplied",
      "symbol": "INO",
      "name": "Inovio Pharmaceuticals, Inc.",
      "marketCap": "$50,894,982",
      "fiscalQuarterEnding": "Dec/2024",
      "epsForecast": "($0.92)",
      "noOfEsts": "2"
    },
    {
      "lastYearRptDt": "3/06/2024",
      "lastYearEPS": "($1.12)",
      "time": "time-not-supplied",
      "symbol": "SDIG",
      "name": "Stronghold Digital Mining, Inc.",
      "marketCap": "$47,590,650",
      "fiscalQuarterEnding": "Dec/2024",
      "epsForecast": "($0.88)",
      "noOfEsts": "1"
    },
    {
      "lastYearRptDt": "3/13/2024",
      "lastYearEPS": "($0.60)",
      "time": "time-not-supplied",
      "symbol": "AADI",
      "name": "Aadi Bioscience, Inc.",
      "marketCap": "$47,569,467",
      "fiscalQuarterEnding": "Dec/2024",
      "epsForecast": "($0.25)",
      "noOfEsts": "3"
    },
    {
      "lastYearRptDt": "N/A",
      "lastYearEPS": "($1.67)",
      "time": "time-not-supplied",
      "symbol": "VTVT",
      "name": "vTv Therapeutics Inc.",
      "marketCap": "$46,440,663",
      "fiscalQuarterEnding": "Dec/2024",
      "epsForecast": "",
      "noOfEsts": "2"
    },
    {
      "lastYearRptDt": "N/A",
      "lastYearEPS": "($0.08)",
      "time": "time-not-supplied",
      "symbol": "RFL",
      "name": "Rafael Holdings, Inc.",
      "marketCap": "$46,387,402",
      "fiscalQuarterEnding": "Jan/2025",
      "epsForecast": "",
      "noOfEsts": "2"
    },
    {
      "lastYearRptDt": "3/13/2024",
      "lastYearEPS": "$0.11",
      "time": "time-after-hours",
      "symbol": "BGSF",
      "name": "BGSF, Inc.",
      "marketCap": "$44,757,493",
      "fiscalQuarterEnding": "Dec/2024",
      "epsForecast": "($0.08)",
      "noOfEsts": "2"
    },
    {
      "lastYearRptDt": "N/A",
      "lastYearEPS": "($0.11)",
      "time": "time-not-supplied",
      "symbol": "OPTT",
      "name": "Ocean Power Technologies, Inc.",
      "marketCap": "$42,621,466",
      "fiscalQuarterEnding": "Jan/2025",
      "epsForecast": "",
      "noOfEsts": "2"
    },
    {
      "lastYearRptDt": "3/13/2024",
      "lastYearEPS": "$0.96",
      "time": "time-not-supplied",
      "symbol": "SPRO",
      "name": "Spero Therapeutics, Inc.",
      "marketCap": "$40,196,243",
      "fiscalQuarterEnding": "Dec/2024",
      "epsForecast": "($0.31)",
      "noOfEsts": "2"
    },
    {
      "lastYearRptDt": "3/13/2024",
      "lastYearEPS": "($1.35)",
      "time": "time-not-supplied",
      "symbol": "GWH",
      "name": "ESS Tech, Inc.",
      "marketCap": "$37,074,558",
      "fiscalQuarterEnding": "Dec/2024",
      "epsForecast": "($1.51)",
      "noOfEsts": "2"
    },
    {
      "lastYearRptDt": "3/13/2024",
      "lastYearEPS": "($1.20)",
      "time": "time-not-supplied",
      "symbol": "CLNN",
      "name": "Clene Inc.",
      "marketCap": "$36,227,956",
      "fiscalQuarterEnding": "Dec/2024",
      "epsForecast": "($1.21)",
      "noOfEsts": "2"
    },
    {
      "lastYearRptDt": "N/A",
      "lastYearEPS": "($0.05)",
      "time": "time-not-supplied",
      "symbol": "MLEC",
      "name": "Moolec Science SA",
      "marketCap": "$35,309,942",
      "fiscalQuarterEnding": "Dec/2024",
      "epsForecast": "",
      "noOfEsts": "2"
    },
    {
      "lastYearRptDt": "3/13/2024",
      "lastYearEPS": "($0.70)",
      "time": "time-not-supplied",
      "symbol": "FTCI",
      "name": "FTC Solar, Inc.",
      "marketCap": "$34,497,139",
      "fiscalQuarterEnding": "Dec/2024",
      "epsForecast": "($0.93)",
      "noOfEsts": "3"
    },
    {
      "lastYearRptDt": "3/06/2024",
      "lastYearEPS": "($0.53)",
      "time": "time-not-supplied",
      "symbol": "GBIO",
      "name": "Generation Bio Co.",
      "marketCap": "$33,924,074",
      "fiscalQuarterEnding": "Dec/2024",
      "epsForecast": "($0.28)",
      "noOfEsts": "3"
    },
    {
      "lastYearRptDt": "N/A",
      "lastYearEPS": "$0.03",
      "time": "time-after-hours",
      "symbol": "ZDGE",
      "name": "Zedge, Inc.",
      "marketCap": "$31,964,391",
      "fiscalQuarterEnding": "Jan/2025",
      "epsForecast": "",
      "noOfEsts": "2"
    },
    {
      "lastYearRptDt": "N/A",
      "lastYearEPS": "N/A",
      "time": "time-not-supplied",
      "symbol": "SDST",
      "name": "Stardust Power Inc.",
      "marketCap": "$30,381,926",
      "fiscalQuarterEnding": "Dec/2024",
      "epsForecast": "($0.07)",
      "noOfEsts": "2"
    },
    {
      "lastYearRptDt": "N/A",
      "lastYearEPS": "N/A",
      "time": "time-not-supplied",
      "symbol": "ROLR",
      "name": "High Roller Technologies, Inc.",
      "marketCap": "$24,966,642",
      "fiscalQuarterEnding": "Dec/2024",
      "epsForecast": "",
      "noOfEsts": "2"
    },
    {
      "lastYearRptDt": "N/A",
      "lastYearEPS": "N/A",
      "time": "time-not-supplied",
      "symbol": "ENZ",
      "name": "Enzo Biochem, Inc.",
      "marketCap": "$23,457,589",
      "fiscalQuarterEnding": "Jan/2025",
      "epsForecast": "",
      "noOfEsts": "2"
    },
    {
      "lastYearRptDt": "N/A",
      "lastYearEPS": "$0.02",
      "time": "time-not-supplied",
      "symbol": "YHGJ",
      "name": "Yunhong Green CTI Ltd.",
      "marketCap": "$18,538,320",
      "fiscalQuarterEnding": "Dec/2024",
      "epsForecast": "",
      "noOfEsts": "2"
    },
    {
      "lastYearRptDt": "3/14/2024",
      "lastYearEPS": "($0.50)",
      "time": "time-after-hours",
      "symbol": "FTHM",
      "name": "Fathom Holdings Inc.",
      "marketCap": "$18,050,963",
      "fiscalQuarterEnding": "Dec/2024",
      "epsForecast": "($0.33)",
      "noOfEsts": "1"
    },
    {
      "lastYearRptDt": "N/A",
      "lastYearEPS": "N/A",
      "time": "time-not-supplied",
      "symbol": "MDRR",
      "name": "Medalist Diversified REIT, Inc.",
      "marketCap": "$17,210,775",
      "fiscalQuarterEnding": "Dec/2024",
      "epsForecast": "",
      "noOfEsts": "2"
    },
    {
      "lastYearRptDt": "3/13/2024",
      "lastYearEPS": "($0.17)",
      "time": "time-not-supplied",
      "symbol": "SLGL",
      "name": "Sol-Gel Technologies Ltd.",
      "marketCap": "$16,488,925",
      "fiscalQuarterEnding": "Dec/2024",
      "epsForecast": "($0.11)",
      "noOfEsts": "1"
    },
    {
      "lastYearRptDt": "3/13/2024",
      "lastYearEPS": "($0.23)",
      "time": "time-not-supplied",
      "symbol": "SPRB",
      "name": "Spruce Biosciences, Inc.",
      "marketCap": "$14,319,611",
      "fiscalQuarterEnding": "Dec/2024",
      "epsForecast": "($0.21)",
      "noOfEsts": "3"
    },
    {
      "lastYearRptDt": "N/A",
      "lastYearEPS": "($0.09)",
      "time": "time-not-supplied",
      "symbol": "PET",
      "name": "Wag! Group Co.",
      "marketCap": "$12,298,407",
      "fiscalQuarterEnding": "Dec/2024",
      "epsForecast": "",
      "noOfEsts": "2"
    },
    {
      "lastYearRptDt": "3/13/2024",
      "lastYearEPS": "($0.64)",
      "time": "time-not-supplied",
      "symbol": "ANY",
      "name": "Sphere 3D Corp.",
      "marketCap": "$11,738,377",
      "fiscalQuarterEnding": "Dec/2024",
      "epsForecast": "($0.27)",
      "noOfEsts": "1"
    },
    {
      "lastYearRptDt": "3/13/2024",
      "lastYearEPS": "($0.52)",
      "time": "time-not-supplied",
      "symbol": "CNTM",
      "name": "ConnectM Technology Solutions, Inc.",
      "marketCap": "$11,026,136",
      "fiscalQuarterEnding": "Dec/2024",
      "epsForecast": "($0.06)",
      "noOfEsts": "1"
    },
    {
      "lastYearRptDt": "2/28/2024",
      "lastYearEPS": "($0.30)",
      "time": "time-not-supplied",
      "symbol": "SNSE",
      "name": "Sensei Biotherapeutics, Inc.",
      "marketCap": "$10,691,851",
      "fiscalQuarterEnding": "Dec/2024",
      "epsForecast": "($0.27)",
      "noOfEsts": "2"
    },
    {
      "lastYearRptDt": "3/06/2024",
      "lastYearEPS": "($0.25)",
      "time": "time-not-supplied",
      "symbol": "TLPH",
      "name": "Talphera, Inc.",
      "marketCap": "$9,366,070",
      "fiscalQuarterEnding": "Dec/2024",
      "epsForecast": "($0.21)",
      "noOfEsts": "1"
    },
    {
      "lastYearRptDt": "3/13/2024",
      "lastYearEPS": "($0.47)",
      "time": "time-not-supplied",
      "symbol": "INDP",
      "name": "Indaptus Therapeutics, Inc.",
      "marketCap": "$8,565,383",
      "fiscalQuarterEnding": "Dec/2024",
      "epsForecast": "($0.41)",
      "noOfEsts": "1"
    },
    {
      "lastYearRptDt": "N/A",
      "lastYearEPS": "($0.35)",
      "time": "time-not-supplied",
      "symbol": "ABVC",
      "name": "ABVC Biopharma, Inc.",
      "marketCap": "$8,498,947",
      "fiscalQuarterEnding": "Dec/2024",
      "epsForecast": "",
      "noOfEsts": "2"
    },
    {
      "lastYearRptDt": "N/A",
      "lastYearEPS": "N/A",
      "time": "time-not-supplied",
      "symbol": "OMEX",
      "name": "Odyssey Marine Exploration, Inc.",
      "marketCap": "$8,435,730",
      "fiscalQuarterEnding": "Dec/2024",
      "epsForecast": "",
      "noOfEsts": "2"
    },
    {
      "lastYearRptDt": "N/A",
      "lastYearEPS": "($2.43)",
      "time": "time-after-hours",
      "symbol": "ULY",
      "name": "Urgent.ly Inc.",
      "marketCap": "$6,925,334",
      "fiscalQuarterEnding": "Dec/2024",
      "epsForecast": "",
      "noOfEsts": "2"
    },
    {
      "lastYearRptDt": "N/A",
      "lastYearEPS": "N/A",
      "time": "time-not-supplied",
      "symbol": "HCWC",
      "name": "Healthy Choice Wellness Corp.",
      "marketCap": "$5,388,846",
      "fiscalQuarterEnding": "Dec/2024",
      "epsForecast": "",
      "noOfEsts": "2"
    },
    {
      "lastYearRptDt": "2/28/2024",
      "lastYearEPS": "($3.60)",
      "time": "time-not-supplied",
      "symbol": "PRTG",
      "name": "Portage Biotech Inc.",
      "marketCap": "$4,372,720",
      "fiscalQuarterEnding": "Dec/2024",
      "epsForecast": "",
      "noOfEsts": "N/A"
    },
    {
      "lastYearRptDt": "3/13/2024",
      "lastYearEPS": "($3.15)",
      "time": "time-not-supplied",
      "symbol": "BOXL",
      "name": "Boxlight Corporation",
      "marketCap": "$3,008,112",
      "fiscalQuarterEnding": "Dec/2024",
      "epsForecast": "",
      "noOfEsts": "N/A"
    },
    {
      "lastYearRptDt": "N/A",
      "lastYearEPS": "N/A",
      "time": "time-after-hours",
      "symbol": "SNES",
      "name": "SenesTech, Inc.",
      "marketCap": "$2,460,073",
      "fiscalQuarterEnding": "Dec/2024",
      "epsForecast": "($1.50)",
      "noOfEsts": "2"
    },
    {
      "lastYearRptDt": "N/A",
      "lastYearEPS": "N/A",
      "time": "time-not-supplied",
      "symbol": "ASTI",
      "name": "Ascent Solar Technologies, Inc",
      "marketCap": "$2,185,927",
      "fiscalQuarterEnding": "Dec/2024",
      "epsForecast": "",
      "noOfEsts": "2"
    },
    {
      "lastYearRptDt": "N/A",
      "lastYearEPS": "($6.80)",
      "time": "time-not-supplied",
      "symbol": "ISPC",
      "name": "iSpecimen Inc.",
      "marketCap": "$1,251,428",
      "fiscalQuarterEnding": "Dec/2024",
      "epsForecast": "",
      "noOfEsts": "2"
    },
    {
      "lastYearRptDt": "N/A",
      "lastYearEPS": "N/A",
      "time": "time-not-supplied",
      "symbol": "CCIX",
      "name": "Churchill Capital Corp IX",
      "marketCap": "",
      "fiscalQuarterEnding": "Dec/2024",
      "epsForecast": "",
      "noOfEsts": "2"
    },
    {
      "lastYearRptDt": "N/A",
      "lastYearEPS": "N/A",
      "time": "time-not-supplied",
      "symbol": "PCSC",
      "name": "Perceptive Capital Solutions Corp",
      "marketCap": "",
      "fiscalQuarterEnding": "Dec/2024",
      "epsForecast": "",
      "noOfEsts": "2"
    }
  ]
}